{
  "generated": "2026-04-15T21:55:03.745173",
  "config": {
    "days": 730
  },
  "strategies": {
    "S00_MFKK_SCORE": {
      "strategy": "MFKK Score",
      "best_tf": "H1",
      "tp": 20.0,
      "sl": 12.0,
      "stats": {
        "n": 223,
        "wr": 43.5,
        "pnl": 428.0,
        "pf": 1.283,
        "dd": 136.0,
        "avg_day": 14.27,
        "pos_months": "3/3",
        "n_buy": 43,
        "n_sell": 180,
        "buy_wr": 37.2,
        "sell_wr": 45.0
      },
      "periods": {
        "1m": {
          "n": 86,
          "pnl": 216.0,
          "wr": 45.3,
          "pf": 1.383,
          "dd": 84.0,
          "avg_td": 2.87,
          "avg_td_active": 7.17
        },
        "6m": {
          "n": 223,
          "pnl": 428.0,
          "wr": 43.5,
          "pf": 1.283,
          "dd": 136.0,
          "avg_td": 1.24,
          "avg_td_active": 7.43
        },
        "12m": {
          "n": 223,
          "pnl": 428.0,
          "wr": 43.5,
          "pf": 1.283,
          "dd": 136.0,
          "avg_td": 0.61,
          "avg_td_active": 7.43
        },
        "24m": {
          "n": 223,
          "pnl": 428.0,
          "wr": 43.5,
          "pf": 1.283,
          "dd": 136.0,
          "avg_td": 0.31,
          "avg_td_active": 7.43
        }
      }
    },
    "S00_MFKK_HWR": {
      "strategy": "MFKK HighWR",
      "stats": null,
      "periods": {}
    },
    "S05_MFKK_INTRADAY": {
      "strategy": "MFKK Intraday",
      "best": {
        "variant": "V2_Triple_MACD",
        "tf": "H4",
        "stats": {
          "n": 82,
          "wr": 42.7,
          "pnl": 1101.5,
          "pf": 1.365,
          "dd": 781.3,
          "avg_day": 44.06,
          "pos_months": "1/3",
          "n_buy": 25,
          "n_sell": 57,
          "buy_wr": 20.0,
          "sell_wr": 52.6
        },
        "periods": {
          "1m": {
            "n": 24,
            "pnl": 723.5,
            "wr": 54.2,
            "pf": 1.812,
            "dd": 623.3,
            "avg_td": 0.8,
            "avg_td_active": 2.67
          },
          "6m": {
            "n": 82,
            "pnl": 1101.5,
            "wr": 42.7,
            "pf": 1.365,
            "dd": 781.3,
            "avg_td": 0.46,
            "avg_td_active": 3.28
          },
          "12m": {
            "n": 82,
            "pnl": 1101.5,
            "wr": 42.7,
            "pf": 1.365,
            "dd": 781.3,
            "avg_td": 0.22,
            "avg_td_active": 3.28
          },
          "24m": {
            "n": 82,
            "pnl": 1101.5,
            "wr": 42.7,
            "pf": 1.365,
            "dd": 781.3,
            "avg_td": 0.11,
            "avg_td_active": 3.28
          }
        },
        "trades": [
          {
            "date": "2026-02-16",
            "hour": 23,
            "dir": "sell",
            "outcome": "win",
            "pnl": 101.42,
            "ts": 1771282800,
            "sl_val": 50.71
          },
          {
            "date": "2026-02-17",
            "hour": 3,
            "dir": "sell",
            "outcome": "loss",
            "pnl": -55.03,
            "ts": 1771297200,
            "sl_val": 55.03
          },
          {
            "date": "2026-02-17",
            "hour": 7,
            "dir": "sell",
            "outcome": "loss",
            "pnl": -51.09,
            "ts": 1771311600,
            "sl_val": 51.09
          },
          {
            "date": "2026-02-17",
            "hour": 11,
            "dir": "sell",
            "outcome": "loss",
            "pnl": -52.64,
            "ts": 1771326000,
            "sl_val": 52.64
          },
          {
            "date": "2026-02-17",
            "hour": 15,
            "dir": "sell",
            "outcome": "loss",
            "pnl": -54.2,
            "ts": 1771340400,
            "sl_val": 54.2
          },
          {
            "date": "2026-02-17",
            "hour": 19,
            "dir": "sell",
            "outcome": "loss",
            "pnl": -52.92,
            "ts": 1771354800,
            "sl_val": 52.92
          },
          {
            "date": "2026-02-17",
            "hour": 23,
            "dir": "sell",
            "outcome": "loss",
            "pnl": -50.72,
            "ts": 1771369200,
            "sl_val": 50.72
          },
          {
            "date": "2026-02-18",
            "hour": 3,
            "dir": "sell",
            "outcome": "loss",
            "pnl": -52.39,
            "ts": 1771383600,
            "sl_val": 52.39
          },
          {
            "date": "2026-02-18",
            "hour": 7,
            "dir": "sell",
            "outcome": "loss",
            "pnl": -50.75,
            "ts": 1771398000,
            "sl_val": 50.75
          },
          {
            "date": "2026-02-19",
            "hour": 11,
            "dir": "buy",
            "outcome": "win",
            "pnl": 89.03,
            "ts": 1771498800,
            "sl_val": 44.51
          },
          {
            "date": "2026-02-19",
            "hour": 15,
            "dir": "buy",
            "outcome": "win",
            "pnl": 90.85,
            "ts": 1771513200,
            "sl_val": 45.43
          },
          {
            "date": "2026-02-19",
            "hour": 19,
            "dir": "buy",
            "outcome": "win",
            "pnl": 84.37,
            "ts": 1771527600,
            "sl_val": 42.18
          },
          {
            "date": "2026-02-23",
            "hour": 11,
            "dir": "buy",
            "outcome": "win",
            "pnl": 82.79,
            "ts": 1771844400,
            "sl_val": 41.4
          },
          {
            "date": "2026-02-23",
            "hour": 15,
            "dir": "buy",
            "outcome": "loss",
            "pnl": -44.88,
            "ts": 1771858800,
            "sl_val": 44.88
          },
          {
            "date": "2026-02-23",
            "hour": 19,
            "dir": "buy",
            "outcome": "loss",
            "pnl": -45.75,
            "ts": 1771873200,
            "sl_val": 45.75
          },
          {
            "date": "2026-02-23",
            "hour": 23,
            "dir": "buy",
            "outcome": "loss",
            "pnl": -49.01,
            "ts": 1771887600,
            "sl_val": 49.01
          },
          {
            "date": "2026-02-24",
            "hour": 3,
            "dir": "buy",
            "outcome": "loss",
            "pnl": -49.15,
            "ts": 1771902000,
            "sl_val": 49.15
          },
          {
            "date": "2026-02-24",
            "hour": 7,
            "dir": "buy",
            "outcome": "loss",
            "pnl": -49.08,
            "ts": 1771916400,
            "sl_val": 49.08
          },
          {
            "date": "2026-02-24",
            "hour": 11,
            "dir": "buy",
            "outcome": "win",
            "pnl": 103.88,
            "ts": 1771930800,
            "sl_val": 51.94
          },
          {
            "date": "2026-03-02",
            "hour": 7,
            "dir": "buy",
            "outcome": "loss",
            "pnl": -48.21,
            "ts": 1772434800,
            "sl_val": 48.21
          },
          {
            "date": "2026-03-02",
            "hour": 11,
            "dir": "buy",
            "outcome": "loss",
            "pnl": -48.94,
            "ts": 1772449200,
            "sl_val": 48.94
          },
          {
            "date": "2026-03-02",
            "hour": 15,
            "dir": "buy",
            "outcome": "loss",
            "pnl": -56.29,
            "ts": 1772463600,
            "sl_val": 56.29
          },
          {
            "date": "2026-03-02",
            "hour": 19,
            "dir": "buy",
            "outcome": "loss",
            "pnl": -58.04,
            "ts": 1772478000,
            "sl_val": 58.04
          },
          {
            "date": "2026-03-02",
            "hour": 23,
            "dir": "buy",
            "outcome": "loss",
            "pnl": -57.72,
            "ts": 1772492400,
            "sl_val": 57.72
          },
          {
            "date": "2026-03-03",
            "hour": 19,
            "dir": "sell",
            "outcome": "loss",
            "pnl": -89.75,
            "ts": 1772564400,
            "sl_val": 89.75
          },
          {
            "date": "2026-03-03",
            "hour": 23,
            "dir": "sell",
            "outcome": "win",
            "pnl": 186.72,
            "ts": 1772578800,
            "sl_val": 93.36
          },
          {
            "date": "2026-03-04",
            "hour": 3,
            "dir": "sell",
            "outcome": "win",
            "pnl": 185.49,
            "ts": 1772593200,
            "sl_val": 92.74
          },
          {
            "date": "2026-03-04",
            "hour": 7,
            "dir": "sell",
            "outcome": "win",
            "pnl": 178.18,
            "ts": 1772607600,
            "sl_val": 89.09
          },
          {
            "date": "2026-03-04",
            "hour": 11,
            "dir": "sell",
            "outcome": "win",
            "pnl": 178.12,
            "ts": 1772622000,
            "sl_val": 89.06
          },
          {
            "date": "2026-03-04",
            "hour": 15,
            "dir": "sell",
            "outcome": "loss",
            "pnl": -89.72,
            "ts": 1772636400,
            "sl_val": 89.72
          },
          {
            "date": "2026-03-04",
            "hour": 19,
            "dir": "sell",
            "outcome": "loss",
            "pnl": -89.44,
            "ts": 1772650800,
            "sl_val": 89.44
          },
          {
            "date": "2026-03-04",
            "hour": 23,
            "dir": "sell",
            "outcome": "win",
            "pnl": 166.07,
            "ts": 1772665200,
            "sl_val": 83.03
          },
          {
            "date": "2026-03-05",
            "hour": 3,
            "dir": "sell",
            "outcome": "loss",
            "pnl": -82.31,
            "ts": 1772679600,
            "sl_val": 82.31
          },
          {
            "date": "2026-03-05",
            "hour": 15,
            "dir": "sell",
            "outcome": "loss",
            "pnl": -81.22,
            "ts": 1772722800,
            "sl_val": 81.22
          },
          {
            "date": "2026-03-05",
            "hour": 19,
            "dir": "sell",
            "outcome": "loss",
            "pnl": -69.09,
            "ts": 1772737200,
            "sl_val": 69.09
          },
          {
            "date": "2026-03-05",
            "hour": 23,
            "dir": "sell",
            "outcome": "loss",
            "pnl": -61.81,
            "ts": 1772751600,
            "sl_val": 61.81
          },
          {
            "date": "2026-03-06",
            "hour": 3,
            "dir": "sell",
            "outcome": "loss",
            "pnl": -58.78,
            "ts": 1772766000,
            "sl_val": 58.78
          },
          {
            "date": "2026-03-06",
            "hour": 7,
            "dir": "sell",
            "outcome": "loss",
            "pnl": -54.86,
            "ts": 1772780400,
            "sl_val": 54.86
          },
          {
            "date": "2026-03-06",
            "hour": 11,
            "dir": "sell",
            "outcome": "loss",
            "pnl": -56.17,
            "ts": 1772794800,
            "sl_val": 56.17
          },
          {
            "date": "2026-03-06",
            "hour": 15,
            "dir": "sell",
            "outcome": "win",
            "pnl": 116.21,
            "ts": 1772809200,
            "sl_val": 58.1
          },
          {
            "date": "2026-03-10",
            "hour": 11,
            "dir": "buy",
            "outcome": "loss",
            "pnl": -65.47,
            "ts": 1773140400,
            "sl_val": 65.47
          },
          {
            "date": "2026-03-10",
            "hour": 15,
            "dir": "buy",
            "outcome": "loss",
            "pnl": -66.43,
            "ts": 1773154800,
            "sl_val": 66.43
          },
          {
            "date": "2026-03-10",
            "hour": 19,
            "dir": "buy",
            "outcome": "loss",
            "pnl": -66.4,
            "ts": 1773169200,
            "sl_val": 66.4
          },
          {
            "date": "2026-03-10",
            "hour": 23,
            "dir": "buy",
            "outcome": "loss",
            "pnl": -62.78,
            "ts": 1773183600,
            "sl_val": 62.78
          },
          {
            "date": "2026-03-11",
            "hour": 3,
            "dir": "buy",
            "outcome": "loss",
            "pnl": -62.28,
            "ts": 1773198000,
            "sl_val": 62.28
          },
          {
            "date": "2026-03-11",
            "hour": 7,
            "dir": "buy",
            "outcome": "loss",
            "pnl": -51.64,
            "ts": 1773212400,
            "sl_val": 51.64
          },
          {
            "date": "2026-03-12",
            "hour": 19,
            "dir": "sell",
            "outcome": "loss",
            "pnl": -45.17,
            "ts": 1773342000,
            "sl_val": 45.17
          },
          {
            "date": "2026-03-12",
            "hour": 23,
            "dir": "sell",
            "outcome": "win",
            "pnl": 90.15,
            "ts": 1773356400,
            "sl_val": 45.08
          },
          {
            "date": "2026-03-13",
            "hour": 3,
            "dir": "sell",
            "outcome": "win",
            "pnl": 84.81,
            "ts": 1773370800,
            "sl_val": 42.4
          },
          {
            "date": "2026-03-13",
            "hour": 7,
            "dir": "sell",
            "outcome": "win",
            "pnl": 85.73,
            "ts": 1773385200,
            "sl_val": 42.87
          },
          {
            "date": "2026-03-13",
            "hour": 11,
            "dir": "sell",
            "outcome": "win",
            "pnl": 87.4,
            "ts": 1773399600,
            "sl_val": 43.7
          },
          {
            "date": "2026-03-13",
            "hour": 15,
            "dir": "sell",
            "outcome": "win",
            "pnl": 95.05,
            "ts": 1773414000,
            "sl_val": 47.53
          },
          {
            "date": "2026-03-13",
            "hour": 19,
            "dir": "sell",
            "outcome": "win",
            "pnl": 94.25,
            "ts": 1773428400,
            "sl_val": 47.13
          },
          {
            "date": "2026-03-15",
            "hour": 23,
            "dir": "sell",
            "outcome": "win",
            "pnl": 97.41,
            "ts": 1773615600,
            "sl_val": 48.71
          },
          {
            "date": "2026-03-16",
            "hour": 3,
            "dir": "sell",
            "outcome": "win",
            "pnl": 99.41,
            "ts": 1773630000,
            "sl_val": 49.7
          },
          {
            "date": "2026-03-16",
            "hour": 7,
            "dir": "sell",
            "outcome": "loss",
            "pnl": -50.09,
            "ts": 1773644400,
            "sl_val": 50.09
          },
          {
            "date": "2026-03-16",
            "hour": 11,
            "dir": "sell",
            "outcome": "win",
            "pnl": 103.95,
            "ts": 1773658800,
            "sl_val": 51.97
          },
          {
            "date": "2026-03-16",
            "hour": 15,
            "dir": "sell",
            "outcome": "win",
            "pnl": 106.93,
            "ts": 1773673200,
            "sl_val": 53.46
          },
          {
            "date": "2026-03-16",
            "hour": 19,
            "dir": "sell",
            "outcome": "win",
            "pnl": 104.92,
            "ts": 1773687600,
            "sl_val": 52.46
          },
          {
            "date": "2026-03-16",
            "hour": 23,
            "dir": "sell",
            "outcome": "win",
            "pnl": 100.91,
            "ts": 1773702000,
            "sl_val": 50.46
          },
          {
            "date": "2026-03-17",
            "hour": 3,
            "dir": "sell",
            "outcome": "win",
            "pnl": 96.2,
            "ts": 1773716400,
            "sl_val": 48.1
          },
          {
            "date": "2026-03-17",
            "hour": 7,
            "dir": "sell",
            "outcome": "win",
            "pnl": 92.28,
            "ts": 1773730800,
            "sl_val": 46.14
          },
          {
            "date": "2026-03-18",
            "hour": 11,
            "dir": "sell",
            "outcome": "win",
            "pnl": 92.98,
            "ts": 1773831600,
            "sl_val": 46.49
          },
          {
            "date": "2026-03-18",
            "hour": 15,
            "dir": "sell",
            "outcome": "win",
            "pnl": 90.0,
            "ts": 1773846000,
            "sl_val": 45.0
          },
          {
            "date": "2026-03-18",
            "hour": 19,
            "dir": "sell",
            "outcome": "loss",
            "pnl": -47.02,
            "ts": 1773860400,
            "sl_val": 47.02
          },
          {
            "date": "2026-03-18",
            "hour": 23,
            "dir": "sell",
            "outcome": "win",
            "pnl": 93.87,
            "ts": 1773874800,
            "sl_val": 46.93
          },
          {
            "date": "2026-03-19",
            "hour": 3,
            "dir": "sell",
            "outcome": "win",
            "pnl": 94.94,
            "ts": 1773889200,
            "sl_val": 47.47
          },
          {
            "date": "2026-03-19",
            "hour": 7,
            "dir": "sell",
            "outcome": "win",
            "pnl": 112.4,
            "ts": 1773903600,
            "sl_val": 56.2
          },
          {
            "date": "2026-03-19",
            "hour": 11,
            "dir": "sell",
            "outcome": "loss",
            "pnl": -69.96,
            "ts": 1773918000,
            "sl_val": 69.96
          },
          {
            "date": "2026-03-19",
            "hour": 15,
            "dir": "sell",
            "outcome": "loss",
            "pnl": -74.14,
            "ts": 1773932400,
            "sl_val": 74.14
          },
          {
            "date": "2026-03-19",
            "hour": 19,
            "dir": "sell",
            "outcome": "loss",
            "pnl": -76.1,
            "ts": 1773946800,
            "sl_val": 76.1
          },
          {
            "date": "2026-03-19",
            "hour": 23,
            "dir": "sell",
            "outcome": "win",
            "pnl": 154.82,
            "ts": 1773961200,
            "sl_val": 77.41
          },
          {
            "date": "2026-03-20",
            "hour": 19,
            "dir": "sell",
            "outcome": "win",
            "pnl": 175.76,
            "ts": 1774033200,
            "sl_val": 87.88
          },
          {
            "date": "2026-03-22",
            "hour": 23,
            "dir": "sell",
            "outcome": "win",
            "pnl": 200.56,
            "ts": 1774220400,
            "sl_val": 100.28
          },
          {
            "date": "2026-03-23",
            "hour": 3,
            "dir": "sell",
            "outcome": "win",
            "pnl": 204.42,
            "ts": 1774234800,
            "sl_val": 102.21
          },
          {
            "date": "2026-03-23",
            "hour": 7,
            "dir": "sell",
            "outcome": "loss",
            "pnl": -112.83,
            "ts": 1774249200,
            "sl_val": 112.83
          },
          {
            "date": "2026-03-23",
            "hour": 11,
            "dir": "sell",
            "outcome": "loss",
            "pnl": -128.0,
            "ts": 1774263600,
            "sl_val": 128.0
          },
          {
            "date": "2026-03-23",
            "hour": 15,
            "dir": "sell",
            "outcome": "loss",
            "pnl": -128.46,
            "ts": 1774278000,
            "sl_val": 128.46
          },
          {
            "date": "2026-04-01",
            "hour": 14,
            "dir": "buy",
            "outcome": "loss",
            "pnl": -62.97,
            "ts": 1775052000,
            "sl_val": 62.97
          },
          {
            "date": "2026-04-01",
            "hour": 18,
            "dir": "buy",
            "outcome": "loss",
            "pnl": -62.53,
            "ts": 1775066400,
            "sl_val": 62.53
          },
          {
            "date": "2026-04-01",
            "hour": 22,
            "dir": "buy",
            "outcome": "loss",
            "pnl": -61.19,
            "ts": 1775080800,
            "sl_val": 61.19
          },
          {
            "date": "2026-04-02",
            "hour": 2,
            "dir": "buy",
            "outcome": "loss",
            "pnl": -67.34,
            "ts": 1775095200,
            "sl_val": 67.34
          }
        ]
      },
      "all_variants": {
        "V1_OBV_RSI_MOM": {
          "M5": {
            "stats": {
              "n": 151,
              "wr": 34.4,
              "pnl": -11.8,
              "pf": 0.988,
              "dd": 212.8,
              "avg_day": -0.18,
              "pos_months": "2/4",
              "n_buy": 71,
              "n_sell": 80,
              "buy_wr": 28.2,
              "sell_wr": 40.0
            },
            "periods": {
              "1m": {
                "n": 50,
                "pnl": -120.5,
                "wr": 26.0,
                "pf": 0.647,
                "dd": 212.8,
                "avg_td": 1.67,
                "avg_td_active": 2.38
              },
              "6m": {
                "n": 151,
                "pnl": -11.8,
                "wr": 34.4,
                "pf": 0.988,
                "dd": 212.8,
                "avg_td": 0.84,
                "avg_td_active": 2.32
              },
              "12m": {
                "n": 151,
                "pnl": -11.8,
                "wr": 34.4,
                "pf": 0.988,
                "dd": 212.8,
                "avg_td": 0.41,
                "avg_td_active": 2.32
              },
              "24m": {
                "n": 151,
                "pnl": -11.8,
                "wr": 34.4,
                "pf": 0.988,
                "dd": 212.8,
                "avg_td": 0.21,
                "avg_td_active": 2.32
              }
            },
            "trades_count": 151
          },
          "M15": {
            "stats": {
              "n": 86,
              "wr": 34.9,
              "pnl": 206.9,
              "pf": 1.23,
              "dd": 243.9,
              "avg_day": 4.14,
              "pos_months": "3/5",
              "n_buy": 42,
              "n_sell": 44,
              "buy_wr": 40.5,
              "sell_wr": 29.5
            },
            "periods": {
              "1m": {
                "n": 18,
                "pnl": -60.2,
                "wr": 33.3,
                "pf": 0.772,
                "dd": 243.9,
                "avg_td": 0.6,
                "avg_td_active": 1.5
              },
              "6m": {
                "n": 86,
                "pnl": 206.9,
                "wr": 34.9,
                "pf": 1.23,
                "dd": 243.9,
                "avg_td": 0.48,
                "avg_td_active": 1.72
              },
              "12m": {
                "n": 86,
                "pnl": 206.9,
                "wr": 34.9,
                "pf": 1.23,
                "dd": 243.9,
                "avg_td": 0.24,
                "avg_td_active": 1.72
              },
              "24m": {
                "n": 86,
                "pnl": 206.9,
                "wr": 34.9,
                "pf": 1.23,
                "dd": 243.9,
                "avg_td": 0.12,
                "avg_td_active": 1.72
              }
            },
            "trades_count": 86
          },
          "M30": {
            "stats": {
              "n": 52,
              "wr": 40.4,
              "pnl": 238.9,
              "pf": 1.429,
              "dd": 135.1,
              "avg_day": 6.64,
              "pos_months": "3/6",
              "n_buy": 25,
              "n_sell": 27,
              "buy_wr": 40.0,
              "sell_wr": 40.7
            },
            "periods": {
              "1m": {
                "n": 6,
                "pnl": -117.0,
                "wr": 0.0,
                "pf": 0.0,
                "dd": 117.0,
                "avg_td": 0.2,
                "avg_td_active": 1.0
              },
              "6m": {
                "n": 52,
                "pnl": 238.9,
                "wr": 40.4,
                "pf": 1.429,
                "dd": 135.1,
                "avg_td": 0.29,
                "avg_td_active": 1.44
              },
              "12m": {
                "n": 52,
                "pnl": 238.9,
                "wr": 40.4,
                "pf": 1.429,
                "dd": 135.1,
                "avg_td": 0.14,
                "avg_td_active": 1.44
              },
              "24m": {
                "n": 52,
                "pnl": 238.9,
                "wr": 40.4,
                "pf": 1.429,
                "dd": 135.1,
                "avg_td": 0.07,
                "avg_td_active": 1.44
              }
            },
            "trades_count": 52
          },
          "H1": {
            "stats": {
              "n": 15,
              "wr": 26.7,
              "pnl": -78.5,
              "pf": 0.745,
              "dd": 223.8,
              "avg_day": -5.23,
              "pos_months": "2/3",
              "n_buy": 6,
              "n_sell": 9,
              "buy_wr": 33.3,
              "sell_wr": 22.2
            },
            "periods": {
              "1m": {
                "n": 6,
                "pnl": 19.6,
                "wr": 33.3,
                "pf": 1.209,
                "dd": 75.9,
                "avg_td": 0.2,
                "avg_td_active": 1.0
              },
              "6m": {
                "n": 15,
                "pnl": -78.5,
                "wr": 26.7,
                "pf": 0.745,
                "dd": 223.8,
                "avg_td": 0.08,
                "avg_td_active": 1.0
              },
              "12m": {
                "n": 15,
                "pnl": -78.5,
                "wr": 26.7,
                "pf": 0.745,
                "dd": 223.8,
                "avg_td": 0.04,
                "avg_td_active": 1.0
              },
              "24m": {
                "n": 15,
                "pnl": -78.5,
                "wr": 26.7,
                "pf": 0.745,
                "dd": 223.8,
                "avg_td": 0.02,
                "avg_td_active": 1.0
              }
            },
            "trades_count": 15
          },
          "H4": {
            "stats": {
              "n": 3,
              "wr": 33.3,
              "pnl": -27.5,
              "pf": 0.787,
              "dd": 128.9,
              "avg_day": -9.17,
              "pos_months": "1/3",
              "n_buy": 1,
              "n_sell": 2,
              "buy_wr": 0.0,
              "sell_wr": 50.0
            },
            "periods": {
              "1m": {
                "n": 1,
                "pnl": -71.7,
                "wr": 0.0,
                "pf": 0.0,
                "dd": 71.7,
                "avg_td": 0.03,
                "avg_td_active": 1.0
              },
              "6m": {
                "n": 3,
                "pnl": -27.5,
                "wr": 33.3,
                "pf": 0.787,
                "dd": 128.9,
                "avg_td": 0.02,
                "avg_td_active": 1.0
              },
              "12m": {
                "n": 3,
                "pnl": -27.5,
                "wr": 33.3,
                "pf": 0.787,
                "dd": 128.9,
                "avg_td": 0.01,
                "avg_td_active": 1.0
              },
              "24m": {
                "n": 3,
                "pnl": -27.5,
                "wr": 33.3,
                "pf": 0.787,
                "dd": 128.9,
                "avg_td": 0.0,
                "avg_td_active": 1.0
              }
            },
            "trades_count": 3
          }
        },
        "V2_Triple_MACD": {
          "M5": {
            "stats": {
              "n": 509,
              "wr": 34.6,
              "pnl": 293.6,
              "pf": 1.098,
              "dd": 455.9,
              "avg_day": 4.25,
              "pos_months": "3/4",
              "n_buy": 231,
              "n_sell": 278,
              "buy_wr": 33.3,
              "sell_wr": 35.6
            },
            "periods": {
              "1m": {
                "n": 158,
                "pnl": 379.9,
                "wr": 39.9,
                "pf": 1.446,
                "dd": 169.0,
                "avg_td": 5.27,
                "avg_td_active": 7.52
              },
              "6m": {
                "n": 509,
                "pnl": 293.6,
                "wr": 34.6,
                "pf": 1.098,
                "dd": 455.9,
                "avg_td": 2.83,
                "avg_td_active": 7.38
              },
              "12m": {
                "n": 509,
                "pnl": 293.6,
                "wr": 34.6,
                "pf": 1.098,
                "dd": 455.9,
                "avg_td": 1.39,
                "avg_td_active": 7.38
              },
              "24m": {
                "n": 509,
                "pnl": 293.6,
                "wr": 34.6,
                "pf": 1.098,
                "dd": 455.9,
                "avg_td": 0.7,
                "avg_td_active": 7.38
              }
            },
            "trades_count": 509
          },
          "M15": {
            "stats": {
              "n": 414,
              "wr": 31.6,
              "pnl": -54.1,
              "pf": 0.987,
              "dd": 837.8,
              "avg_day": -0.64,
              "pos_months": "2/5",
              "n_buy": 197,
              "n_sell": 217,
              "buy_wr": 30.5,
              "sell_wr": 32.7
            },
            "periods": {
              "1m": {
                "n": 109,
                "pnl": -286.2,
                "wr": 31.2,
                "pf": 0.792,
                "dd": 680.9,
                "avg_td": 3.63,
                "avg_td_active": 5.19
              },
              "6m": {
                "n": 414,
                "pnl": -54.1,
                "wr": 31.6,
                "pf": 0.987,
                "dd": 837.8,
                "avg_td": 2.3,
                "avg_td_active": 4.93
              },
              "12m": {
                "n": 414,
                "pnl": -54.1,
                "wr": 31.6,
                "pf": 0.987,
                "dd": 837.8,
                "avg_td": 1.13,
                "avg_td_active": 4.93
              },
              "24m": {
                "n": 414,
                "pnl": -54.1,
                "wr": 31.6,
                "pf": 0.987,
                "dd": 837.8,
                "avg_td": 0.57,
                "avg_td_active": 4.93
              }
            },
            "trades_count": 414
          },
          "M30": {
            "stats": {
              "n": 396,
              "wr": 34.3,
              "pnl": 333.3,
              "pf": 1.064,
              "dd": 1036.4,
              "avg_day": 3.7,
              "pos_months": "4/6",
              "n_buy": 207,
              "n_sell": 189,
              "buy_wr": 34.3,
              "sell_wr": 34.4
            },
            "periods": {
              "1m": {
                "n": 74,
                "pnl": 533.9,
                "wr": 43.2,
                "pf": 1.492,
                "dd": 459.9,
                "avg_td": 2.47,
                "avg_td_active": 4.62
              },
              "6m": {
                "n": 396,
                "pnl": 333.3,
                "wr": 34.3,
                "pf": 1.064,
                "dd": 1036.4,
                "avg_td": 2.2,
                "avg_td_active": 4.4
              },
              "12m": {
                "n": 396,
                "pnl": 333.3,
                "wr": 34.3,
                "pf": 1.064,
                "dd": 1036.4,
                "avg_td": 1.08,
                "avg_td_active": 4.4
              },
              "24m": {
                "n": 396,
                "pnl": 333.3,
                "wr": 34.3,
                "pf": 1.064,
                "dd": 1036.4,
                "avg_td": 0.54,
                "avg_td_active": 4.4
              }
            },
            "trades_count": 396
          },
          "H1": {
            "stats": {
              "n": 258,
              "wr": 34.9,
              "pnl": 543.5,
              "pf": 1.095,
              "dd": 1320.6,
              "avg_day": 13.26,
              "pos_months": "2/3",
              "n_buy": 116,
              "n_sell": 142,
              "buy_wr": 32.8,
              "sell_wr": 36.6
            },
            "periods": {
              "1m": {
                "n": 103,
                "pnl": 704.7,
                "wr": 38.8,
                "pf": 1.335,
                "dd": 844.6,
                "avg_td": 3.43,
                "avg_td_active": 6.87
              },
              "6m": {
                "n": 258,
                "pnl": 543.5,
                "wr": 34.9,
                "pf": 1.095,
                "dd": 1320.6,
                "avg_td": 1.43,
                "avg_td_active": 6.29
              },
              "12m": {
                "n": 258,
                "pnl": 543.5,
                "wr": 34.9,
                "pf": 1.095,
                "dd": 1320.6,
                "avg_td": 0.71,
                "avg_td_active": 6.29
              },
              "24m": {
                "n": 258,
                "pnl": 543.5,
                "wr": 34.9,
                "pf": 1.095,
                "dd": 1320.6,
                "avg_td": 0.35,
                "avg_td_active": 6.29
              }
            },
            "trades_count": 258
          },
          "H4": {
            "stats": {
              "n": 82,
              "wr": 42.7,
              "pnl": 1101.5,
              "pf": 1.365,
              "dd": 781.3,
              "avg_day": 44.06,
              "pos_months": "1/3",
              "n_buy": 25,
              "n_sell": 57,
              "buy_wr": 20.0,
              "sell_wr": 52.6
            },
            "periods": {
              "1m": {
                "n": 24,
                "pnl": 723.5,
                "wr": 54.2,
                "pf": 1.812,
                "dd": 623.3,
                "avg_td": 0.8,
                "avg_td_active": 2.67
              },
              "6m": {
                "n": 82,
                "pnl": 1101.5,
                "wr": 42.7,
                "pf": 1.365,
                "dd": 781.3,
                "avg_td": 0.46,
                "avg_td_active": 3.28
              },
              "12m": {
                "n": 82,
                "pnl": 1101.5,
                "wr": 42.7,
                "pf": 1.365,
                "dd": 781.3,
                "avg_td": 0.22,
                "avg_td_active": 3.28
              },
              "24m": {
                "n": 82,
                "pnl": 1101.5,
                "wr": 42.7,
                "pf": 1.365,
                "dd": 781.3,
                "avg_td": 0.11,
                "avg_td_active": 3.28
              }
            },
            "trades_count": 82
          }
        },
        "V3_Sell_Exhaustion": {
          "M5": {
            "stats": {
              "n": 7,
              "wr": 42.9,
              "pnl": 18.7,
              "pf": 1.607,
              "dd": 23.8,
              "avg_day": 3.12,
              "pos_months": "1/3",
              "n_buy": 0,
              "n_sell": 7,
              "buy_wr": 0,
              "sell_wr": 42.9
            },
            "periods": {
              "1m": {
                "n": 1,
                "pnl": 25.8,
                "wr": 100.0,
                "pf": 25790.0,
                "dd": 0,
                "avg_td": 0.03,
                "avg_td_active": 1.0
              },
              "6m": {
                "n": 7,
                "pnl": 18.7,
                "wr": 42.9,
                "pf": 1.607,
                "dd": 23.8,
                "avg_td": 0.04,
                "avg_td_active": 1.17
              },
              "12m": {
                "n": 7,
                "pnl": 18.7,
                "wr": 42.9,
                "pf": 1.607,
                "dd": 23.8,
                "avg_td": 0.02,
                "avg_td_active": 1.17
              },
              "24m": {
                "n": 7,
                "pnl": 18.7,
                "wr": 42.9,
                "pf": 1.607,
                "dd": 23.8,
                "avg_td": 0.01,
                "avg_td_active": 1.17
              }
            },
            "trades_count": 7
          },
          "M15": {
            "stats": {
              "n": 3,
              "wr": 66.7,
              "pnl": 26.3,
              "pf": 4.768,
              "dd": 7.0,
              "avg_day": 13.15,
              "pos_months": "2/2",
              "n_buy": 0,
              "n_sell": 3,
              "buy_wr": 0,
              "sell_wr": 66.7
            },
            "periods": {
              "1m": {
                "n": 0,
                "pnl": 0,
                "wr": 0,
                "pf": 0,
                "dd": 0,
                "avg_td": 0.0,
                "avg_td_active": 0.0
              },
              "6m": {
                "n": 3,
                "pnl": 26.3,
                "wr": 66.7,
                "pf": 4.768,
                "dd": 7.0,
                "avg_td": 0.02,
                "avg_td_active": 1.5
              },
              "12m": {
                "n": 3,
                "pnl": 26.3,
                "wr": 66.7,
                "pf": 4.768,
                "dd": 7.0,
                "avg_td": 0.01,
                "avg_td_active": 1.5
              },
              "24m": {
                "n": 3,
                "pnl": 26.3,
                "wr": 66.7,
                "pf": 4.768,
                "dd": 7.0,
                "avg_td": 0.0,
                "avg_td_active": 1.5
              }
            },
            "trades_count": 3
          },
          "M30": {
            "stats": {
              "n": 9,
              "wr": 22.2,
              "pnl": -48.8,
              "pf": 0.586,
              "dd": 75.0,
              "avg_day": -6.97,
              "pos_months": "1/4",
              "n_buy": 0,
              "n_sell": 9,
              "buy_wr": 0,
              "sell_wr": 22.2
            },
            "periods": {
              "1m": {
                "n": 2,
                "pnl": -56.8,
                "wr": 0.0,
                "pf": 0.0,
                "dd": 56.8,
                "avg_td": 0.07,
                "avg_td_active": 2.0
              },
              "6m": {
                "n": 9,
                "pnl": -48.8,
                "wr": 22.2,
                "pf": 0.586,
                "dd": 75.0,
                "avg_td": 0.05,
                "avg_td_active": 1.29
              },
              "12m": {
                "n": 9,
                "pnl": -48.8,
                "wr": 22.2,
                "pf": 0.586,
                "dd": 75.0,
                "avg_td": 0.02,
                "avg_td_active": 1.29
              },
              "24m": {
                "n": 9,
                "pnl": -48.8,
                "wr": 22.2,
                "pf": 0.586,
                "dd": 75.0,
                "avg_td": 0.01,
                "avg_td_active": 1.29
              }
            },
            "trades_count": 9
          },
          "H1": {
            "stats": {
              "n": 2,
              "wr": 0.0,
              "pnl": -47.5,
              "pf": 0.0,
              "dd": 47.5,
              "avg_day": -47.55,
              "pos_months": "0/1",
              "n_buy": 0,
              "n_sell": 2,
              "buy_wr": 0,
              "sell_wr": 0.0
            },
            "periods": {
              "1m": {
                "n": 0,
                "pnl": 0,
                "wr": 0,
                "pf": 0,
                "dd": 0,
                "avg_td": 0.0,
                "avg_td_active": 0.0
              },
              "6m": {
                "n": 2,
                "pnl": -47.5,
                "wr": 0.0,
                "pf": 0.0,
                "dd": 47.5,
                "avg_td": 0.01,
                "avg_td_active": 2.0
              },
              "12m": {
                "n": 2,
                "pnl": -47.5,
                "wr": 0.0,
                "pf": 0.0,
                "dd": 47.5,
                "avg_td": 0.01,
                "avg_td_active": 2.0
              },
              "24m": {
                "n": 2,
                "pnl": -47.5,
                "wr": 0.0,
                "pf": 0.0,
                "dd": 47.5,
                "avg_td": 0.0,
                "avg_td_active": 2.0
              }
            },
            "trades_count": 2
          },
          "H4": {
            "stats": null,
            "periods": {},
            "trades_count": 0
          }
        },
        "V4_Strong_5cond": {
          "M5": {
            "stats": {
              "n": 12,
              "wr": 33.3,
              "pnl": -68.2,
              "pf": 0.493,
              "dd": 107.5,
              "avg_day": -6.2,
              "pos_months": "2/4",
              "n_buy": 1,
              "n_sell": 11,
              "buy_wr": 0.0,
              "sell_wr": 36.4
            },
            "periods": {
              "1m": {
                "n": 3,
                "pnl": 32.8,
                "wr": 66.7,
                "pf": 6.107,
                "dd": 6.4,
                "avg_td": 0.1,
                "avg_td_active": 1.0
              },
              "6m": {
                "n": 12,
                "pnl": -68.2,
                "wr": 33.3,
                "pf": 0.493,
                "dd": 107.5,
                "avg_td": 0.07,
                "avg_td_active": 1.09
              },
              "12m": {
                "n": 12,
                "pnl": -68.2,
                "wr": 33.3,
                "pf": 0.493,
                "dd": 107.5,
                "avg_td": 0.03,
                "avg_td_active": 1.09
              },
              "24m": {
                "n": 12,
                "pnl": -68.2,
                "wr": 33.3,
                "pf": 0.493,
                "dd": 107.5,
                "avg_td": 0.02,
                "avg_td_active": 1.09
              }
            },
            "trades_count": 12
          },
          "M15": {
            "stats": {
              "n": 13,
              "wr": 23.1,
              "pnl": -113.5,
              "pf": 0.449,
              "dd": 148.9,
              "avg_day": -8.73,
              "pos_months": "1/5",
              "n_buy": 2,
              "n_sell": 11,
              "buy_wr": 50.0,
              "sell_wr": 18.2
            },
            "periods": {
              "1m": {
                "n": 3,
                "pnl": -72.2,
                "wr": 0.0,
                "pf": 0.0,
                "dd": 72.2,
                "avg_td": 0.1,
                "avg_td_active": 1.0
              },
              "6m": {
                "n": 13,
                "pnl": -113.5,
                "wr": 23.1,
                "pf": 0.449,
                "dd": 148.9,
                "avg_td": 0.07,
                "avg_td_active": 1.0
              },
              "12m": {
                "n": 13,
                "pnl": -113.5,
                "wr": 23.1,
                "pf": 0.449,
                "dd": 148.9,
                "avg_td": 0.04,
                "avg_td_active": 1.0
              },
              "24m": {
                "n": 13,
                "pnl": -113.5,
                "wr": 23.1,
                "pf": 0.449,
                "dd": 148.9,
                "avg_td": 0.02,
                "avg_td_active": 1.0
              }
            },
            "trades_count": 13
          },
          "M30": {
            "stats": {
              "n": 4,
              "wr": 50.0,
              "pnl": 21.7,
              "pf": 1.638,
              "dd": 17.9,
              "avg_day": 7.23,
              "pos_months": "1/1",
              "n_buy": 0,
              "n_sell": 4,
              "buy_wr": 0,
              "sell_wr": 50.0
            },
            "periods": {
              "1m": {
                "n": 0,
                "pnl": 0,
                "wr": 0,
                "pf": 0,
                "dd": 0,
                "avg_td": 0.0,
                "avg_td_active": 0.0
              },
              "6m": {
                "n": 4,
                "pnl": 21.7,
                "wr": 50.0,
                "pf": 1.638,
                "dd": 17.9,
                "avg_td": 0.02,
                "avg_td_active": 1.33
              },
              "12m": {
                "n": 4,
                "pnl": 21.7,
                "wr": 50.0,
                "pf": 1.638,
                "dd": 17.9,
                "avg_td": 0.01,
                "avg_td_active": 1.33
              },
              "24m": {
                "n": 4,
                "pnl": 21.7,
                "wr": 50.0,
                "pf": 1.638,
                "dd": 17.9,
                "avg_td": 0.01,
                "avg_td_active": 1.33
              }
            },
            "trades_count": 4
          },
          "H1": {
            "stats": null,
            "periods": {},
            "trades_count": 0
          },
          "H4": {
            "stats": null,
            "periods": {},
            "trades_count": 0
          }
        }
      }
    }
  }
}